setup.py
tommy/__init__.py
tommy.egg-info/PKG-INFO
tommy.egg-info/SOURCES.txt
tommy.egg-info/dependency_links.txt
tommy.egg-info/not-zip-safe
tommy.egg-info/top_level.txt