Metadata-Version: 1.0
Name: tommy
Version: 0.1
Summary: Modular virtual assistan
Home-page: https://github.com/amark97/tommy
Author: amark, SoAwesomeMan
Author-email: alexandre.markiewicz.1997@gmail.com, callme@1800AWESO.ME
License: MIT
Platform: UNKNOWN
